{
    "name": "cvrp60-5-rj-1",
    "vehicles": [
        {
            "deliveries": [
                {
                    "id": "97834055d83f9aa8f4a7020f88bb3431",
                    "point": {
                        "lat": -23.002073207010024,
                        "lng": -43.358039309732725
                    },
                    "size": 6.0
                },
                {
                    "id": "7f58851faca15839aa4226fdc0f1362d",
                    "point": {
                        "lat": -23.00076374780222,
                        "lng": -43.35951190476329
                    },
                    "size": 6.0
                },
                {
                    "id": "832ef6b531ffb56226ee42b2954fa34a",
                    "point": {
                        "lat": -23.00135441761016,
                        "lng": -43.36069346800345
                    },
                    "size": 4.0
                },
                {
                    "id": "f7d597402f7d95692a063eeaf6c9ad21",
                    "point": {
                        "lat": -23.001771716303455,
                        "lng": -43.360586385154775
                    },
                    "size": 2.0
                },
                {
                    "id": "e6d5802129062f46bec42a2db5b980fe",
                    "point": {
                        "lat": -23.00262966016577,
                        "lng": -43.360641777357074
                    },
                    "size": 2.0
                },
                {
                    "id": "a7bfdbb972e4e48b3153b78c9286d732",
                    "point": {
                        "lat": -23.00239128096595,
                        "lng": -43.36202415522366
                    },
                    "size": 3.0
                },
                {
                    "id": "236286a374806b37155b2930cac879db",
                    "point": {
                        "lat": -23.001280882954475,
                        "lng": -43.36294330919667
                    },
                    "size": 2.0
                },
                {
                    "id": "2ad217a827307ee82ceeed67b6dffb77",
                    "point": {
                        "lat": -23.001161822736716,
                        "lng": -43.368686383873474
                    },
                    "size": 4.0
                },
                {
                    "id": "63aa9e527ceeb0a78c9a2e39027fd653",
                    "point": {
                        "lat": -23.00095724784029,
                        "lng": -43.36898731796434
                    },
                    "size": 6.0
                },
                {
                    "id": "777070a8076e119cd716c52d4352b159",
                    "point": {
                        "lat": -23.00242196703669,
                        "lng": -43.36852502652237
                    },
                    "size": 5.0
                },
                {
                    "id": "9728a9dfb46c2c74f1031670945705bf",
                    "point": {
                        "lat": -23.0049408494947,
                        "lng": -43.37160528089117
                    },
                    "size": 1.0
                },
                {
                    "id": "24a5ceb3277a4c3baa33b671cb72ab27",
                    "point": {
                        "lat": -23.008688745110522,
                        "lng": -43.36980740324834
                    },
                    "size": 7.0
                },
                {
                    "id": "378bfdae5782dafb124b3ea697f4733d",
                    "point": {
                        "lat": -23.008968369199398,
                        "lng": -43.36964292814893
                    },
                    "size": 5.0
                },
                {
                    "id": "c3872407deeb8fd43cfb3623621ac5e7",
                    "point": {
                        "lat": -23.008702810041544,
                        "lng": -43.36897503768572
                    },
                    "size": 5.0
                },
                {
                    "id": "1235c759b0ee4074c1319f81b5cb93ed",
                    "point": {
                        "lat": -23.009269982182808,
                        "lng": -43.36939328172359
                    },
                    "size": 2.0
                },
                {
                    "id": "7e60171b651d82d33b44696db46b5180",
                    "point": {
                        "lat": -23.010332770517955,
                        "lng": -43.37138395247958
                    },
                    "size": 5.0
                },
                {
                    "id": "33fa17f041106ed9de13ce3ccbde3a53",
                    "point": {
                        "lat": -23.010639745482152,
                        "lng": -43.37070723480847
                    },
                    "size": 8.0
                },
                {
                    "id": "a88982d7b1444f7e3acba90e777fc957",
                    "point": {
                        "lat": -23.011025787157177,
                        "lng": -43.36955208211513
                    },
                    "size": 4.0
                },
                {
                    "id": "41adf24a36560d92349701630e4ae35",
                    "point": {
                        "lat": -23.01012308446384,
                        "lng": -43.36927455695619
                    },
                    "size": 3.0
                },
                {
                    "id": "9dc26065dae007a2aad20b07fcdf4c9a",
                    "point": {
                        "lat": -23.00959502141795,
                        "lng": -43.36840427796334
                    },
                    "size": 2.0
                },
                {
                    "id": "6f358da928c48d15544fe70b062fab77",
                    "point": {
                        "lat": -23.009584954678964,
                        "lng": -43.36839762660448
                    },
                    "size": 4.0
                },
                {
                    "id": "953de463e0c20f2d12975a9bafe5ba48",
                    "point": {
                        "lat": -23.009969903736724,
                        "lng": -43.36793465383533
                    },
                    "size": 5.0
                },
                {
                    "id": "1eda6d933cd5e6360416fa1d1140de3a",
                    "point": {
                        "lat": -23.010343121154964,
                        "lng": -43.36771319933972
                    },
                    "size": 1.0
                },
                {
                    "id": "5b9ea8aa8a580c4ca4442cc90dd82603",
                    "point": {
                        "lat": -23.010774519484478,
                        "lng": -43.367287473641525
                    },
                    "size": 5.0
                },
                {
                    "id": "a69462ad38b4609f6dd78a12f25c5b5c",
                    "point": {
                        "lat": -23.01102327896475,
                        "lng": -43.36702151459079
                    },
                    "size": 3.0
                },
                {
                    "id": "da423970149bbc1f43a03d7e5c786125",
                    "point": {
                        "lat": -23.011044071601773,
                        "lng": -43.36689563106255
                    },
                    "size": 10.0
                },
                {
                    "id": "8869364ec704f61a5208e57235a2cff0",
                    "point": {
                        "lat": -23.010485733393715,
                        "lng": -43.366295523633895
                    },
                    "size": 6.0
                },
                {
                    "id": "202711cd68fcb3b3c8a4a20e58c0d001",
                    "point": {
                        "lat": -23.009496391785124,
                        "lng": -43.366747818737
                    },
                    "size": 4.0
                },
                {
                    "id": "456e358963554ef12448e0a83b286528",
                    "point": {
                        "lat": -23.0089053042349,
                        "lng": -43.366989589242216
                    },
                    "size": 5.0
                },
                {
                    "id": "5b73b86249b9d2028119f28b05317cbb",
                    "point": {
                        "lat": -23.00884797724657,
                        "lng": -43.36716707786367
                    },
                    "size": 3.0
                },
                {
                    "id": "36e841e8cfb32dfd233e6a3859a50e8a",
                    "point": {
                        "lat": -23.00890281451312,
                        "lng": -43.36726121328704
                    },
                    "size": 3.0
                },
                {
                    "id": "d18d7c405834a49c424c455a1140f9e1",
                    "point": {
                        "lat": -23.008944905602092,
                        "lng": -43.36746065531544
                    },
                    "size": 5.0
                },
                {
                    "id": "3920afe971cdeb5d9b2967f313d7fb7",
                    "point": {
                        "lat": -23.008724910182597,
                        "lng": -43.367411232828935
                    },
                    "size": 3.0
                },
                {
                    "id": "f55eaf01eee62d13042ffda45a8495dd",
                    "point": {
                        "lat": -23.008534346315447,
                        "lng": -43.367077907176125
                    },
                    "size": 3.0
                },
                {
                    "id": "1dc075a5d64ca22fa1ae6c05711c9466",
                    "point": {
                        "lat": -23.008545831881506,
                        "lng": -43.36658206583196
                    },
                    "size": 2.0
                },
                {
                    "id": "fcc8b9e33414b97cf6f42810bedf4238",
                    "point": {
                        "lat": -23.00991678262753,
                        "lng": -43.36500085153312
                    },
                    "size": 2.0
                },
                {
                    "id": "c1f9d736fb04c396221c26448d031ec2",
                    "point": {
                        "lat": -23.009839379478887,
                        "lng": -43.3641034141269
                    },
                    "size": 6.0
                },
                {
                    "id": "a0c0ccbe62faf3f123620e698054d4c8",
                    "point": {
                        "lat": -23.010040840687903,
                        "lng": -43.36384367641274
                    },
                    "size": 7.0
                },
                {
                    "id": "9ae09c86649bdd5aa3ff4425cdc639a",
                    "point": {
                        "lat": -23.01003373887699,
                        "lng": -43.3635859784381
                    },
                    "size": 6.0
                },
                {
                    "id": "9ae09c86649bdd5aa3ff4425cdc639a",
                    "point": {
                        "lat": -23.01003373887699,
                        "lng": -43.3635859784381
                    },
                    "size": 6.0
                },
                {
                    "id": "d544a595f37eccc1a601c55f5512155",
                    "point": {
                        "lat": -23.008976887184307,
                        "lng": -43.35775496284649
                    },
                    "size": 3.0
                }
            ],
            "origin": {
                "lat": -23.005796236612643,
                "lng": -43.348890120765155
            }
        },
        {
            "deliveries": [
                {
                    "id": "f76cd58252e2ffed94cabd7e1fea3ffc",
                    "point": {
                        "lat": -23.010179271693485,
                        "lng": -43.35778538908732
                    },
                    "size": 3.0
                },
                {
                    "id": "aea7ad3f5fad0b9cb6988fb187469c48",
                    "point": {
                        "lat": -23.010081047111974,
                        "lng": -43.35965742785738
                    },
                    "size": 5.0
                },
                {
                    "id": "a7b01998b964d11bb95aab99df48ab3f",
                    "point": {
                        "lat": -23.00872644122644,
                        "lng": -43.364526715859846
                    },
                    "size": 1.0
                },
                {
                    "id": "ceab3b80ab7ba06928bc0c464396b77e",
                    "point": {
                        "lat": -23.008808348026463,
                        "lng": -43.36493320340343
                    },
                    "size": 7.0
                },
                {
                    "id": "dd0d4f38a844e32e65f5d60f5929ec32",
                    "point": {
                        "lat": -23.00901635203265,
                        "lng": -43.36501094064563
                    },
                    "size": 8.0
                },
                {
                    "id": "1aa1274f8af8a32721fe79fd996d7133",
                    "point": {
                        "lat": -23.009106173485964,
                        "lng": -43.36511897664685
                    },
                    "size": 5.0
                },
                {
                    "id": "786bc9c152f2ee5a710ac6a29afd41db",
                    "point": {
                        "lat": -23.009102663207226,
                        "lng": -43.365187908912986
                    },
                    "size": 6.0
                },
                {
                    "id": "d8c3c34b0a1bd17aa549d5d14775d757",
                    "point": {
                        "lat": -23.00904693992875,
                        "lng": -43.365355042281195
                    },
                    "size": 8.0
                },
                {
                    "id": "cf1eb296dbff5116d1d2ab941b0abb47",
                    "point": {
                        "lat": -23.0084771607668,
                        "lng": -43.36684729369183
                    },
                    "size": 9.0
                },
                {
                    "id": "8cdb585fa17cb959017706e0721153c3",
                    "point": {
                        "lat": -23.008099062731628,
                        "lng": -43.36693421125205
                    },
                    "size": 2.0
                },
                {
                    "id": "69a44c6f4485e205affe8995256825f9",
                    "point": {
                        "lat": -23.00814269141711,
                        "lng": -43.36671632702747
                    },
                    "size": 7.0
                },
                {
                    "id": "84fd02302a67a900b91b4df9d617780c",
                    "point": {
                        "lat": -23.007926051093392,
                        "lng": -43.36665752342233
                    },
                    "size": 5.0
                },
                {
                    "id": "8bc8e2ef29cc0977d8bd680b350fc7f0",
                    "point": {
                        "lat": -23.008193211677547,
                        "lng": -43.366375491971844
                    },
                    "size": 2.0
                },
                {
                    "id": "d5d1e6601693078e6308c2241883aaf1",
                    "point": {
                        "lat": -23.008274491849942,
                        "lng": -43.3654555646567
                    },
                    "size": 10.0
                },
                {
                    "id": "de633e53ab0ce9ef80f0b24be1a75ba4",
                    "point": {
                        "lat": -23.00614842792103,
                        "lng": -43.36356281422484
                    },
                    "size": 1.0
                },
                {
                    "id": "b8dfafb2cd4961a588b04821add3064c",
                    "point": {
                        "lat": -23.00433129298058,
                        "lng": -43.363789926924014
                    },
                    "size": 7.0
                },
                {
                    "id": "587d435c14e47076cee93904d5db7b0e",
                    "point": {
                        "lat": -23.003685293394188,
                        "lng": -43.36259095155785
                    },
                    "size": 8.0
                },
                {
                    "id": "c5550af4762464a037b3a8ee1cc6903b",
                    "point": {
                        "lat": -23.005018303606814,
                        "lng": -43.36111470373494
                    },
                    "size": 5.0
                },
                {
                    "id": "b4433917ad4c811baa7f9d2e1f6ae932",
                    "point": {
                        "lat": -23.004236825715424,
                        "lng": -43.35737510385492
                    },
                    "size": 5.0
                }
            ],
            "origin": {
                "lat": -23.005796236612643,
                "lng": -43.348890120765155
            }
        }
    ]
}
